typing_as_t/__init__.py
typing_as_t/codemod.py
typing_as_t/entrypoint.py
typing_as_t-1.0.1.dist-info/LICENSE
typing_as_t-1.0.1.dist-info/METADATA
typing_as_t-1.0.1.dist-info/WHEEL
typing_as_t-1.0.1.dist-info/entry_points.txt
typing_as_t-1.0.1.dist-info/RECORD
