Metadata-Version: 2.1
Name: typing-as-t
Version: 1.0.1
Summary: LibCST codemod to transform typing imports
Home-page: https://github.com/jaykv/import-typing-as-t
Author: Jay
Author-email: jay.github0@gmail.com
Requires-Python: >=3.9,<4.0
Classifier: Programming Language :: Python :: 3
Classifier: Programming Language :: Python :: 3.9
Classifier: Programming Language :: Python :: 3.10
Classifier: Programming Language :: Python :: 3.11
Classifier: Programming Language :: Python :: 3.12
Requires-Dist: libcst (>=1.3.1,<2.0.0)
Project-URL: Repository, https://github.com/jaykv/import-typing-as-t
